mca_sdk/__init__.py
mca_sdk/py.typed
mca_sdk/buffering/__init__.py
mca_sdk/buffering/exporters.py
mca_sdk/buffering/queue.py
mca_sdk/buffering/retry.py
mca_sdk/config/__init__.py
mca_sdk/config/settings.py
mca_sdk/core/__init__.py
mca_sdk/core/client.py
mca_sdk/core/providers.py
mca_sdk/integrations/__init__.py
mca_sdk/integrations/bridge.py
mca_sdk/integrations/decorators.py
mca_sdk/integrations/genai.py
mca_sdk/registry/__init__.py
mca_sdk/registry/client.py
mca_sdk/registry/models.py
mca_sdk/registry/telemetry.py
mca_sdk/utils/__init__.py
mca_sdk/utils/exceptions.py
mca_sdk/utils/version_check.py
mca_sdk/validation/__init__.py
mca_sdk/validation/attributes.py
mca_sdk/validation/schema.py
mca_sdk-0.1.0.dist-info/licenses/LICENSE
mca_sdk-0.1.0.dist-info/METADATA
mca_sdk-0.1.0.dist-info/WHEEL
mca_sdk-0.1.0.dist-info/top_level.txt
mca_sdk-0.1.0.dist-info/RECORD
