Metadata-Version: 2.4
Name: mca-sdk
Version: 0.1.0
Summary: Model & Clinical AI (MCA) SDK for HIPAA-compliant OpenTelemetry instrumentation
Home-page: https://github.com/baptisthealth/mca-sdk
Author: Baptist Health South Florida
Author-email: Baptist Health South Florida <mlops@baptisthealth.net>
Maintainer-email: Baptist Health South Florida <mlops@baptisthealth.net>
License-Expression: Apache-2.0
Project-URL: Homepage, https://github.com/baptisthealth/mca-sdk
Project-URL: Documentation, https://github.com/baptisthealth/mca-sdk#readme
Project-URL: Repository, https://github.com/baptisthealth/mca-sdk
Project-URL: Bug Tracker, https://github.com/baptisthealth/mca-sdk/issues
Keywords: opentelemetry,monitoring,telemetry,healthcare,hipaa,ml,ai
Classifier: Development Status :: 4 - Beta
Classifier: Intended Audience :: Developers
Classifier: Intended Audience :: Healthcare Industry
Classifier: Topic :: Software Development :: Libraries :: Python Modules
Classifier: Topic :: System :: Monitoring
Classifier: Programming Language :: Python :: 3
Classifier: Programming Language :: Python :: 3.10
Classifier: Programming Language :: Python :: 3.11
Classifier: Programming Language :: Python :: 3.12
Classifier: Operating System :: OS Independent
Requires-Python: >=3.10
License-File: LICENSE
Requires-Dist: opentelemetry-api>=1.20.0
Requires-Dist: opentelemetry-sdk>=1.20.0
Requires-Dist: opentelemetry-exporter-otlp-proto-http>=1.20.0
Requires-Dist: pyyaml>=6.0
Provides-Extra: dev
Requires-Dist: pytest>=7.0.0; extra == "dev"
Requires-Dist: pytest-cov>=4.0.0; extra == "dev"
Requires-Dist: pytest-mock>=3.10.0; extra == "dev"
Requires-Dist: pytest-asyncio>=0.21.0; extra == "dev"
Requires-Dist: black>=23.0.0; extra == "dev"
Requires-Dist: flake8>=6.0.0; extra == "dev"
Requires-Dist: mypy>=1.0.0; extra == "dev"
Requires-Dist: pip-audit==2.10.0; extra == "dev"
Requires-Dist: wheel>=0.46.2; extra == "dev"
Provides-Extra: genai
Requires-Dist: litellm>=1.61.15; extra == "genai"
Provides-Extra: vendor
Requires-Dist: requests>=2.32.4; extra == "vendor"
Provides-Extra: all
Requires-Dist: pytest>=7.0.0; extra == "all"
Requires-Dist: pytest-cov>=4.0.0; extra == "all"
Requires-Dist: pytest-mock>=3.10.0; extra == "all"
Requires-Dist: pytest-asyncio>=0.21.0; extra == "all"
Requires-Dist: black>=23.0.0; extra == "all"
Requires-Dist: flake8>=6.0.0; extra == "all"
Requires-Dist: mypy>=1.0.0; extra == "all"
Requires-Dist: pip-audit==2.10.0; extra == "all"
Requires-Dist: requests>=2.32.4; extra == "all"
Dynamic: author
Dynamic: home-page
Dynamic: license-file
Dynamic: requires-python
